[
  {
    "id": "population",
    "title": "日本の人口（万人）はどう推移した？",
    "data": [
      { "x": 1990, "y": 12361 },
      { "x": 1995, "y": 12557 },
      { "x": 2000, "y": 12693 },
      { "x": 2005, "y": 12777 },
      { "x": 2010, "y": 12806 },
      { "x": 2015, "y": 12710 },
      { "x": 2020, "y": 12615 }
    ],
    "drawStartX": 2005,
    "unit": "万人",
    "yFormat": ",.0f",
    "precision": 0,
    "yExtent": 1.2,
    "buttonText": "答え合わせ",
    "drawPrompt": ["線を描いて", "予想してみよう"],
    "afterRevealHTML": "日本の人口は2008年の約1億2808万人をピークに減少に転じました。"
  },
  {
    "id": "visitors",
    "title": "訪日外国人数（万人）はどう増えた？",
    "data": [
      { "x": 2003, "y": 521 },
      { "x": 2005, "y": 673 },
      { "x": 2007, "y": 835 },
      { "x": 2009, "y": 679 },
      { "x": 2011, "y": 622 },
      { "x": 2013, "y": 1036 },
      { "x": 2015, "y": 1974 },
      { "x": 2017, "y": 2869 },
      { "x": 2019, "y": 3188 }
    ],
    "drawStartX": 2011,
    "unit": "万人",
    "yFormat": ",.0f",
    "precision": 0,
    "yExtent": 1.5,
    "colors": { "known": "#e67e22", "actual": "#2ecc71", "user": "#ffc700" },
    "buttonText": "答え合わせ",
    "drawPrompt": ["線を描いて", "予想してみよう"],
    "afterRevealHTML": "訪日外国人は2011年の東日本大震災後に急回復し、2019年には3188万人に達しました。"
  }
]
